{"symbol":"AMC","name_th":"Asia Metal","name_en":"Asia Metal Public Company Limited","sector":"อื่นๆ","market":"SET","currency":"THB","date":"2026-07-06","price":2.1,"chg":0,"score":{"tech":24,"mom":58,"composite":47,"signal":"REDUCE","entry":0,"stop":0,"target":0,"rr":null,"indicators":{"ema20":2.13,"ema50":2.19,"ema200":2.2,"rsi":39.37,"macd":-0.04,"macdSignal":-0.04,"macdHist":0.01,"atr":0.03,"adx":39.57,"plusDI":12.1,"minusDI":33.54,"stochK":50,"stochD":50,"bbUpper":2.2,"bbLower":2.05,"roc20":-2.78},"reasons":[{"ic":"📉","t":"ราคาต่ำกว่า EMA200 — แนวโน้มใหญ่เป็นขาลง","pts":-8},{"ic":"📉","t":"ราคาต่ำกว่า EMA50 — แนวโน้มกลางเป็นลบ","pts":-6},{"ic":"💀","t":"Dead cross: EMA50 ตัด EMA200 ลง","pts":-10},{"ic":"🥶","t":"RSI 39.37 — โซน oversold/อ่อนแรง","pts":-4},{"ic":"🚀","t":"MACD histogram เป็นบวก — โมเมนตัมหนุน","pts":6},{"ic":"🧭","t":"ADX 39.57 (>25) แนวโน้มลงแข็งแรง, -DI เหนือ +DI","pts":-8},{"ic":"🔊","t":"OBV เพิ่มขึ้น — แรงซื้อสะสม","pts":4}],"signalTech":"AVOID","weights":{"tech":0.45,"fund":0.3,"mom":0.15,"sentiment":0.1}},"fundamentals":{"fund":59,"grade":"C","longTerm":false,"incomplete":false,"ratios":{"pe":69.33,"pbv":0.3,"roe":0.5,"roa":0.2,"de":0.43,"divYield":3.8,"epsGrowth":0,"revGrowth":-12.4,"netMargin":0.3,"payout":266.7,"mktcap":999,"beta":0.26},"reasons":[{"ic":"🔴","t":"P/E 69.33 — แพง (เกิน 30 เท่า)","pts":-6},{"ic":"💎","t":"P/BV 0.3 — ต่ำกว่ามูลค่าทางบัญชี","pts":8},{"ic":"🔻","t":"ROE 0.5% — ต่ำ/อ่อนแอ","pts":-6},{"ic":"🛡️","t":"D/E 0.43 — หนี้ต่ำ ฐานะการเงินแข็ง","pts":5},{"ic":"💵","t":"ปันผล 3.8% — ดี","pts":5},{"ic":"📈","t":"กำไรโต 0% YoY","pts":3}]},"sentiment":{"score":0.9,"summary":"AMC ราคาหุ้นพุ่งสูงทำ All Time High และคาดการณ์กำไรปีนี้จะเติบโตอย่างแข็งแกร่ง หลังจาก 6 เดือนแรกทำกำไรได้ถึง 578.27 ล้านบาท","risks":"ความผันผวนของราคาเหล็ก, การแข่งขันในอุตสาหกรรมโลหะ","positives":"ผลประกอบการที่แข็งแกร่ง, ราคาหุ้นทำ All Time High","score100":95},"news":[{"title":"AMC พุ่งกระฉูด 22% “ออลไทม์ไฮ” ลุ้นกำไรปีนี้โตแรง! หลัง 6 เดือนแรกแตะ 578.27 ลบ.","publisher":"ข่าวหุ้นธุรกิจออนไลน์","url":"https://news.google.com/rss/articles/CBMiVkFVX3lxTE1NS1lSMzhuYlcydkNqYlF2YUM2dUhlQUZwV3U2WUxKTW90TGVOOXdmTktqdEp4RFlqVW56SDB4QnhXekt2LU44ejVLRl9wUjR6LVpneF93?oc=5","ts":"2021-08-20T07:00:00.000Z"}],"bars":[{"date":"2024-07-08","open":3.26,"high":3.28,"low":3.26,"close":3.26,"adjclose":2.98,"volume":63700},{"date":"2024-07-09","open":3.26,"high":3.26,"low":3.26,"close":3.26,"adjclose":2.98,"volume":0},{"date":"2024-07-10","open":3.28,"high":3.3,"low":3.28,"close":3.28,"adjclose":3,"volume":2700},{"date":"2024-07-11","open":3.28,"high":3.28,"low":3.28,"close":3.28,"adjclose":3,"volume":0},{"date":"2024-07-12","open":3.28,"high":3.28,"low":3.28,"close":3.28,"adjclose":3,"volume":0},{"date":"2024-07-15","open":3.28,"high":3.28,"low":3.28,"close":3.28,"adjclose":3,"volume":0},{"date":"2024-07-16","open":3.32,"high":3.32,"low":3.28,"close":3.28,"adjclose":3,"volume":48300},{"date":"2024-07-17","open":3.28,"high":3.28,"low":3.28,"close":3.28,"adjclose":3,"volume":0},{"date":"2024-07-18","open":3.3,"high":3.3,"low":3.28,"close":3.3,"adjclose":3.02,"volume":118000},{"date":"2024-07-19","open":3.3,"high":3.3,"low":3.28,"close":3.28,"adjclose":3,"volume":5100},{"date":"2024-07-23","open":3.26,"high":3.3,"low":3.2,"close":3.3,"adjclose":3.02,"volume":259900},{"date":"2024-07-24","open":3.28,"high":3.3,"low":3.24,"close":3.28,"adjclose":3,"volume":92700},{"date":"2024-07-25","open":3.26,"high":3.26,"low":3.24,"close":3.26,"adjclose":2.98,"volume":28500},{"date":"2024-07-26","open":3.26,"high":3.3,"low":3.24,"close":3.28,"adjclose":3,"volume":41300},{"date":"2024-07-30","open":3.28,"high":3.28,"low":3.28,"close":3.28,"adjclose":3,"volume":0},{"date":"2024-07-31","open":3.28,"high":3.28,"low":3.24,"close":3.26,"adjclose":2.98,"volume":61500},{"date":"2024-08-01","open":3.24,"high":3.28,"low":3.24,"close":3.28,"adjclose":3,"volume":185600},{"date":"2024-08-02","open":3.28,"high":3.28,"low":3.28,"close":3.28,"adjclose":3,"volume":0},{"date":"2024-08-05","open":3.2,"high":3.24,"low":3.16,"close":3.2,"adjclose":2.93,"volume":159600},{"date":"2024-08-06","open":3.14,"high":3.22,"low":3.12,"close":3.22,"adjclose":2.95,"volume":149900},{"date":"2024-08-07","open":3.22,"high":3.22,"low":3.2,"close":3.22,"adjclose":2.95,"volume":38600},{"date":"2024-08-08","open":3.22,"high":3.22,"low":3.22,"close":3.22,"adjclose":2.95,"volume":0},{"date":"2024-08-09","open":3.2,"high":3.2,"low":3.16,"close":3.18,"adjclose":2.91,"volume":81300},{"date":"2024-08-13","open":3.16,"high":3.18,"low":3.1,"close":3.18,"adjclose":2.91,"volume":177700},{"date":"2024-08-14","open":3.12,"high":3.18,"low":3.1,"close":3.18,"adjclose":2.91,"volume":124000},{"date":"2024-08-15","open":3.18,"high":3.18,"low":3.18,"close":3.18,"adjclose":2.91,"volume":0},{"date":"2024-08-16","open":3.18,"high":3.18,"low":3.08,"close":3.16,"adjclose":2.89,"volume":209200},{"date":"2024-08-19","open":3.16,"high":3.16,"low":3.16,"close":3.16,"adjclose":2.89,"volume":0},{"date":"2024-08-20","open":3.16,"high":3.18,"low":3.16,"close":3.18,"adjclose":2.91,"volume":25400},{"date":"2024-08-21","open":3.16,"high":3.16,"low":3.14,"close":3.14,"adjclose":2.87,"volume":2100},{"date":"2024-08-22","open":3.14,"high":3.14,"low":3.14,"close":3.14,"adjclose":2.87,"volume":0},{"date":"2024-08-23","open":3.2,"high":3.22,"low":3.16,"close":3.2,"adjclose":2.93,"volume":140000},{"date":"2024-08-26","open":3.22,"high":3.26,"low":3.22,"close":3.24,"adjclose":2.96,"volume":97000},{"date":"2024-08-27","open":3.26,"high":3.28,"low":3.24,"close":3.24,"adjclose":2.96,"volume":91400},{"date":"2024-08-28","open":3.28,"high":3.28,"low":3.24,"close":3.26,"adjclose":2.98,"volume":5500},{"date":"2024-08-29","open":3.22,"high":3.24,"low":3.22,"close":3.24,"adjclose":2.96,"volume":2500},{"date":"2024-08-30","open":3.22,"high":3.24,"low":3.18,"close":3.24,"adjclose":2.96,"volume":124600},{"date":"2024-09-02","open":3.24,"high":3.24,"low":3.24,"close":3.24,"adjclose":2.96,"volume":0},{"date":"2024-09-03","open":3.24,"high":3.24,"low":3.24,"close":3.24,"adjclose":2.96,"volume":0},{"date":"2024-09-04","open":3.24,"high":3.24,"low":3.24,"close":3.24,"adjclose":2.96,"volume":0},{"date":"2024-09-05","open":3.2,"high":3.22,"low":3.18,"close":3.22,"adjclose":2.95,"volume":121900},{"date":"2024-09-06","open":3.22,"high":3.24,"low":3.2,"close":3.24,"adjclose":2.96,"volume":127700},{"date":"2024-09-09","open":3.24,"high":3.24,"low":3.24,"close":3.24,"adjclose":2.96,"volume":0},{"date":"2024-09-10","open":3.18,"high":3.22,"low":3.18,"close":3.22,"adjclose":2.95,"volume":3100},{"date":"2024-09-11","open":3.22,"high":3.22,"low":3.18,"close":3.22,"adjclose":2.95,"volume":4800},{"date":"2024-09-12","open":3.22,"high":3.22,"low":3.2,"close":3.2,"adjclose":2.93,"volume":1600},{"date":"2024-09-13","open":3.18,"high":3.22,"low":3.18,"close":3.22,"adjclose":2.95,"volume":91500},{"date":"2024-09-16","open":3.22,"high":3.22,"low":3.22,"close":3.22,"adjclose":2.95,"volume":0},{"date":"2024-09-17","open":3.22,"high":3.22,"low":3.22,"close":3.22,"adjclose":2.95,"volume":0},{"date":"2024-09-18","open":3.22,"high":3.22,"low":3.22,"close":3.22,"adjclose":2.95,"volume":0},{"date":"2024-09-19","open":3.22,"high":3.22,"low":3.22,"close":3.22,"adjclose":2.95,"volume":0},{"date":"2024-09-20","open":3.22,"high":3.22,"low":3.22,"close":3.22,"adjclose":2.95,"volume":0},{"date":"2024-09-23","open":3.24,"high":3.26,"low":3.22,"close":3.22,"adjclose":2.95,"volume":70100},{"date":"2024-09-24","open":3.24,"high":3.26,"low":3.2,"close":3.26,"adjclose":2.98,"volume":63600},{"date":"2024-09-25","open":3.26,"high":3.5,"low":3.26,"close":3.32,"adjclose":3.04,"volume":1924200},{"date":"2024-09-26","open":3.32,"high":3.34,"low":3.28,"close":3.28,"adjclose":3,"volume":503200},{"date":"2024-09-27","open":3.28,"high":3.28,"low":3.28,"close":3.28,"adjclose":3,"volume":0},{"date":"2024-09-30","open":3.28,"high":3.32,"low":3.28,"close":3.28,"adjclose":3,"volume":306500},{"date":"2024-10-01","open":3.28,"high":3.28,"low":3.28,"close":3.28,"adjclose":3,"volume":0},{"date":"2024-10-02","open":3.3,"high":3.52,"low":3.26,"close":3.3,"adjclose":3.02,"volume":2725400},{"date":"2024-10-03","open":3.32,"high":3.36,"low":3.3,"close":3.32,"adjclose":3.04,"volume":205000},{"date":"2024-10-04","open":3.32,"high":3.32,"low":3.32,"close":3.32,"adjclose":3.04,"volume":0},{"date":"2024-10-07","open":3.36,"high":3.38,"low":3.34,"close":3.38,"adjclose":3.09,"volume":49700},{"date":"2024-10-08","open":3.38,"high":3.38,"low":3.34,"close":3.36,"adjclose":3.07,"volume":135300},{"date":"2024-10-09","open":3.34,"high":3.38,"low":3.34,"close":3.36,"adjclose":3.07,"volume":40500},{"date":"2024-10-10","open":3.36,"high":3.36,"low":3.32,"close":3.36,"adjclose":3.07,"volume":4700},{"date":"2024-10-11","open":3.36,"high":3.36,"low":3.36,"close":3.36,"adjclose":3.07,"volume":0},{"date":"2024-10-15","open":3.36,"high":3.36,"low":3.3,"close":3.34,"adjclose":3.06,"volume":48000},{"date":"2024-10-16","open":3.34,"high":3.34,"low":3.34,"close":3.34,"adjclose":3.06,"volume":0},{"date":"2024-10-17","open":3.3,"high":3.34,"low":3.3,"close":3.34,"adjclose":3.06,"volume":37300},{"date":"2024-10-18","open":3.3,"high":3.34,"low":3.3,"close":3.34,"adjclose":3.06,"volume":59000},{"date":"2024-10-21","open":3.32,"high":3.32,"low":3.28,"close":3.28,"adjclose":3,"volume":43800},{"date":"2024-10-22","open":3.28,"high":3.28,"low":3.28,"close":3.28,"adjclose":3,"volume":0},{"date":"2024-10-24","open":3.26,"high":3.3,"low":3.26,"close":3.28,"adjclose":3,"volume":4700},{"date":"2024-10-25","open":3.28,"high":3.28,"low":3.28,"close":3.28,"adjclose":3,"volume":0},{"date":"2024-10-28","open":3.22,"high":3.26,"low":3.2,"close":3.26,"adjclose":2.98,"volume":77000},{"date":"2024-10-29","open":3.26,"high":3.26,"low":3.26,"close":3.26,"adjclose":2.98,"volume":0},{"date":"2024-10-30","open":3.24,"high":3.24,"low":3.2,"close":3.2,"adjclose":2.93,"volume":180200},{"date":"2024-10-31","open":3.22,"high":3.22,"low":3.2,"close":3.22,"adjclose":2.95,"volume":26300},{"date":"2024-11-01","open":3.2,"high":3.22,"low":3.2,"close":3.22,"adjclose":2.95,"volume":33000},{"date":"2024-11-04","open":3.2,"high":3.2,"low":3.2,"close":3.2,"adjclose":2.93,"volume":19500},{"date":"2024-11-05","open":3.22,"high":3.24,"low":3.18,"close":3.18,"adjclose":2.91,"volume":70200},{"date":"2024-11-06","open":3.2,"high":3.2,"low":3.2,"close":3.2,"adjclose":2.93,"volume":15500},{"date":"2024-11-07","open":3.18,"high":3.2,"low":3.18,"close":3.2,"adjclose":2.93,"volume":25400},{"date":"2024-11-08","open":3.22,"high":3.22,"low":3.14,"close":3.2,"adjclose":2.93,"volume":135000},{"date":"2024-11-11","open":3.14,"high":3.16,"low":3.14,"close":3.16,"adjclose":2.89,"volume":42700},{"date":"2024-11-12","open":3.14,"high":3.16,"low":3.14,"close":3.16,"adjclose":2.89,"volume":800},{"date":"2024-11-13","open":3.14,"high":3.2,"low":3.12,"close":3.2,"adjclose":2.93,"volume":141700},{"date":"2024-11-14","open":3.16,"high":3.16,"low":3,"close":3.06,"adjclose":2.8,"volume":279000},{"date":"2024-11-15","open":3,"high":3.02,"low":2.92,"close":2.96,"adjclose":2.71,"volume":178900},{"date":"2024-11-18","open":2.96,"high":2.96,"low":2.88,"close":2.88,"adjclose":2.63,"volume":184300},{"date":"2024-11-19","open":2.92,"high":3,"low":2.92,"close":2.94,"adjclose":2.69,"volume":69900},{"date":"2024-11-20","open":2.96,"high":2.96,"low":2.92,"close":2.94,"adjclose":2.69,"volume":108400},{"date":"2024-11-21","open":2.92,"high":2.92,"low":2.9,"close":2.92,"adjclose":2.67,"volume":48600},{"date":"2024-11-22","open":2.9,"high":2.98,"low":2.9,"close":2.96,"adjclose":2.71,"volume":800},{"date":"2024-11-25","open":2.9,"high":2.92,"low":2.88,"close":2.9,"adjclose":2.65,"volume":25900},{"date":"2024-11-26","open":2.88,"high":2.9,"low":2.86,"close":2.9,"adjclose":2.65,"volume":42300},{"date":"2024-11-27","open":2.86,"high":2.86,"low":2.84,"close":2.86,"adjclose":2.62,"volume":15200},{"date":"2024-11-28","open":2.86,"high":2.86,"low":2.84,"close":2.84,"adjclose":2.6,"volume":13800},{"date":"2024-11-29","open":2.84,"high":2.9,"low":2.82,"close":2.86,"adjclose":2.62,"volume":14700},{"date":"2024-12-02","open":2.84,"high":2.88,"low":2.8,"close":2.88,"adjclose":2.63,"volume":75600},{"date":"2024-12-03","open":2.86,"high":2.86,"low":2.76,"close":2.76,"adjclose":2.52,"volume":155400},{"date":"2024-12-04","open":2.76,"high":2.82,"low":2.76,"close":2.82,"adjclose":2.58,"volume":47500},{"date":"2024-12-06","open":2.82,"high":2.84,"low":2.82,"close":2.82,"adjclose":2.58,"volume":14900},{"date":"2024-12-09","open":2.82,"high":2.84,"low":2.76,"close":2.84,"adjclose":2.6,"volume":48300},{"date":"2024-12-11","open":2.82,"high":2.82,"low":2.78,"close":2.82,"adjclose":2.58,"volume":26600},{"date":"2024-12-12","open":2.8,"high":2.84,"low":2.8,"close":2.84,"adjclose":2.6,"volume":18900},{"date":"2024-12-13","open":2.84,"high":2.84,"low":2.78,"close":2.8,"adjclose":2.56,"volume":13300},{"date":"2024-12-16","open":2.82,"high":2.82,"low":2.8,"close":2.82,"adjclose":2.58,"volume":1000},{"date":"2024-12-17","open":2.82,"high":2.82,"low":2.78,"close":2.8,"adjclose":2.56,"volume":9300},{"date":"2024-12-18","open":2.8,"high":2.82,"low":2.78,"close":2.78,"adjclose":2.54,"volume":13300},{"date":"2024-12-19","open":2.76,"high":2.76,"low":2.74,"close":2.76,"adjclose":2.52,"volume":49400},{"date":"2024-12-20","open":2.76,"high":2.76,"low":2.72,"close":2.76,"adjclose":2.52,"volume":35600},{"date":"2024-12-23","open":2.74,"high":2.76,"low":2.18,"close":2.2,"adjclose":2.01,"volume":4784700},{"date":"2024-12-24","open":2.26,"high":2.3,"low":1.87,"close":1.98,"adjclose":1.81,"volume":6816400},{"date":"2024-12-25","open":1.98,"high":2.02,"low":1.7,"close":1.81,"adjclose":1.66,"volume":18243900},{"date":"2024-12-26","open":1.82,"high":1.87,"low":1.82,"close":1.83,"adjclose":1.67,"volume":2212600},{"date":"2024-12-27","open":1.84,"high":1.84,"low":1.79,"close":1.82,"adjclose":1.66,"volume":1070600},{"date":"2024-12-30","open":1.81,"high":1.83,"low":1.81,"close":1.81,"adjclose":1.66,"volume":128000},{"date":"2025-01-02","open":1.81,"high":1.84,"low":1.8,"close":1.83,"adjclose":1.67,"volume":1247000},{"date":"2025-01-03","open":1.83,"high":2.08,"low":1.83,"close":1.91,"adjclose":1.75,"volume":6345000},{"date":"2025-01-06","open":1.92,"high":1.95,"low":1.87,"close":1.87,"adjclose":1.71,"volume":1082600},{"date":"2025-01-07","open":1.89,"high":1.94,"low":1.88,"close":1.94,"adjclose":1.77,"volume":412000},{"date":"2025-01-08","open":1.94,"high":1.96,"low":1.94,"close":1.94,"adjclose":1.77,"volume":497800},{"date":"2025-01-09","open":1.95,"high":1.95,"low":1.88,"close":1.9,"adjclose":1.74,"volume":484800},{"date":"2025-01-10","open":1.87,"high":1.92,"low":1.87,"close":1.9,"adjclose":1.74,"volume":381500},{"date":"2025-01-13","open":1.9,"high":1.92,"low":1.89,"close":1.91,"adjclose":1.75,"volume":241700},{"date":"2025-01-14","open":1.92,"high":1.93,"low":1.89,"close":1.89,"adjclose":1.73,"volume":97200},{"date":"2025-01-15","open":1.91,"high":1.94,"low":1.91,"close":1.92,"adjclose":1.76,"volume":169100},{"date":"2025-01-16","open":1.92,"high":1.96,"low":1.92,"close":1.96,"adjclose":1.79,"volume":482400},{"date":"2025-01-17","open":1.97,"high":1.97,"low":1.92,"close":1.92,"adjclose":1.76,"volume":138800},{"date":"2025-01-20","open":1.94,"high":1.95,"low":1.92,"close":1.95,"adjclose":1.78,"volume":269700},{"date":"2025-01-21","open":1.95,"high":1.96,"low":1.93,"close":1.94,"adjclose":1.77,"volume":151200},{"date":"2025-01-22","open":1.95,"high":1.95,"low":1.94,"close":1.95,"adjclose":1.78,"volume":151100},{"date":"2025-01-23","open":1.95,"high":1.95,"low":1.94,"close":1.95,"adjclose":1.78,"volume":125200},{"date":"2025-01-24","open":1.94,"high":1.95,"low":1.94,"close":1.95,"adjclose":1.78,"volume":34300},{"date":"2025-01-27","open":1.95,"high":1.95,"low":1.94,"close":1.94,"adjclose":1.77,"volume":250800},{"date":"2025-01-28","open":1.94,"high":1.95,"low":1.94,"close":1.95,"adjclose":1.78,"volume":205200},{"date":"2025-01-29","open":1.95,"high":1.96,"low":1.94,"close":1.96,"adjclose":1.79,"volume":305600},{"date":"2025-01-30","open":1.95,"high":1.96,"low":1.95,"close":1.95,"adjclose":1.78,"volume":88200},{"date":"2025-01-31","open":1.95,"high":1.97,"low":1.94,"close":1.97,"adjclose":1.8,"volume":425800},{"date":"2025-02-03","open":1.95,"high":1.96,"low":1.94,"close":1.96,"adjclose":1.79,"volume":60100},{"date":"2025-02-04","open":1.96,"high":1.96,"low":1.94,"close":1.96,"adjclose":1.79,"volume":45700},{"date":"2025-02-05","open":1.95,"high":1.95,"low":1.92,"close":1.93,"adjclose":1.77,"volume":70200},{"date":"2025-02-06","open":1.95,"high":1.95,"low":1.9,"close":1.92,"adjclose":1.76,"volume":192500},{"date":"2025-02-07","open":1.91,"high":1.95,"low":1.9,"close":1.95,"adjclose":1.78,"volume":155000},{"date":"2025-02-10","open":1.94,"high":1.95,"low":1.9,"close":1.94,"adjclose":1.77,"volume":148800},{"date":"2025-02-11","open":1.94,"high":1.94,"low":1.94,"close":1.94,"adjclose":1.77,"volume":500},{"date":"2025-02-13","open":1.93,"high":1.95,"low":1.92,"close":1.95,"adjclose":1.78,"volume":113200},{"date":"2025-02-14","open":1.95,"high":1.96,"low":1.95,"close":1.96,"adjclose":1.79,"volume":13000},{"date":"2025-02-17","open":1.94,"high":1.96,"low":1.93,"close":1.96,"adjclose":1.79,"volume":135900},{"date":"2025-02-18","open":1.96,"high":1.96,"low":1.95,"close":1.95,"adjclose":1.78,"volume":61900},{"date":"2025-02-19","open":1.95,"high":1.96,"low":1.95,"close":1.96,"adjclose":1.79,"volume":36900},{"date":"2025-02-20","open":1.96,"high":1.97,"low":1.96,"close":1.96,"adjclose":1.79,"volume":190900},{"date":"2025-02-21","open":1.97,"high":1.97,"low":1.96,"close":1.97,"adjclose":1.8,"volume":11400},{"date":"2025-02-24","open":1.9,"high":1.92,"low":1.9,"close":1.92,"adjclose":1.76,"volume":46200},{"date":"2025-02-25","open":1.92,"high":1.94,"low":1.9,"close":1.9,"adjclose":1.74,"volume":122600},{"date":"2025-02-26","open":1.93,"high":1.93,"low":1.9,"close":1.92,"adjclose":1.76,"volume":16800},{"date":"2025-02-27","open":1.93,"high":1.93,"low":1.91,"close":1.91,"adjclose":1.75,"volume":54200},{"date":"2025-02-28","open":1.9,"high":1.9,"low":1.88,"close":1.9,"adjclose":1.74,"volume":121300},{"date":"2025-03-03","open":1.9,"high":1.9,"low":1.85,"close":1.87,"adjclose":1.71,"volume":183900},{"date":"2025-03-04","open":1.87,"high":1.9,"low":1.87,"close":1.89,"adjclose":1.73,"volume":47100},{"date":"2025-03-05","open":1.89,"high":1.89,"low":1.88,"close":1.89,"adjclose":1.73,"volume":37400},{"date":"2025-03-06","open":1.89,"high":1.89,"low":1.89,"close":1.89,"adjclose":1.73,"volume":2500},{"date":"2025-03-07","open":1.89,"high":1.9,"low":1.89,"close":1.9,"adjclose":1.74,"volume":16800},{"date":"2025-03-10","open":1.9,"high":1.91,"low":1.89,"close":1.89,"adjclose":1.73,"volume":23300},{"date":"2025-03-11","open":1.91,"high":1.96,"low":1.91,"close":1.95,"adjclose":1.78,"volume":320900},{"date":"2025-03-12","open":1.95,"high":1.95,"low":1.94,"close":1.95,"adjclose":1.78,"volume":248300},{"date":"2025-03-13","open":1.95,"high":1.96,"low":1.94,"close":1.95,"adjclose":1.78,"volume":255500},{"date":"2025-03-14","open":1.96,"high":1.97,"low":1.95,"close":1.97,"adjclose":1.8,"volume":54800},{"date":"2025-03-17","open":1.96,"high":1.97,"low":1.96,"close":1.97,"adjclose":1.8,"volume":32700},{"date":"2025-03-18","open":1.97,"high":1.97,"low":1.95,"close":1.95,"adjclose":1.78,"volume":195400},{"date":"2025-03-19","open":1.98,"high":2,"low":1.97,"close":2,"adjclose":1.83,"volume":184500},{"date":"2025-03-20","open":1.95,"high":1.97,"low":1.95,"close":1.97,"adjclose":1.9,"volume":483900},{"date":"2025-03-21","open":1.95,"high":1.96,"low":1.95,"close":1.96,"adjclose":1.89,"volume":124900},{"date":"2025-03-24","open":1.96,"high":1.97,"low":1.96,"close":1.96,"adjclose":1.89,"volume":43100},{"date":"2025-03-25","open":1.96,"high":1.96,"low":1.95,"close":1.96,"adjclose":1.89,"volume":37700},{"date":"2025-03-26","open":1.96,"high":1.96,"low":1.96,"close":1.96,"adjclose":1.89,"volume":6200},{"date":"2025-03-27","open":1.96,"high":1.97,"low":1.96,"close":1.97,"adjclose":1.9,"volume":4200},{"date":"2025-03-28","open":1.95,"high":1.95,"low":1.95,"close":1.95,"adjclose":1.88,"volume":1200},{"date":"2025-03-31","open":1.95,"high":2.22,"low":1.95,"close":1.99,"adjclose":1.92,"volume":758600},{"date":"2025-04-01","open":2.02,"high":2.02,"low":1.98,"close":2,"adjclose":1.93,"volume":43400},{"date":"2025-04-02","open":1.99,"high":1.99,"low":1.97,"close":1.97,"adjclose":1.9,"volume":34700},{"date":"2025-04-03","open":1.98,"high":1.98,"low":1.98,"close":1.98,"adjclose":1.91,"volume":100},{"date":"2025-04-04","open":1.96,"high":2.04,"low":1.96,"close":2.04,"adjclose":1.96,"volume":77200},{"date":"2025-04-08","open":2.02,"high":2.12,"low":2.02,"close":2.12,"adjclose":2.04,"volume":1369200},{"date":"2025-04-09","open":2.12,"high":2.18,"low":2.1,"close":2.16,"adjclose":2.08,"volume":220900},{"date":"2025-04-10","open":2.12,"high":2.22,"low":2.04,"close":2.18,"adjclose":2.1,"volume":401200},{"date":"2025-04-11","open":2.2,"high":2.22,"low":2.2,"close":2.2,"adjclose":2.12,"volume":343500},{"date":"2025-04-16","open":2.22,"high":2.24,"low":2.22,"close":2.24,"adjclose":2.16,"volume":11200},{"date":"2025-04-17","open":2.2,"high":2.26,"low":2.2,"close":2.24,"adjclose":2.16,"volume":270600},{"date":"2025-04-18","open":2.2,"high":2.24,"low":2.2,"close":2.24,"adjclose":2.16,"volume":55500},{"date":"2025-04-21","open":2.2,"high":2.22,"low":2.2,"close":2.22,"adjclose":2.14,"volume":73900},{"date":"2025-04-22","open":2.22,"high":2.22,"low":2.2,"close":2.22,"adjclose":2.14,"volume":5400},{"date":"2025-04-23","open":2.22,"high":2.22,"low":2.22,"close":2.22,"adjclose":2.14,"volume":2000},{"date":"2025-04-24","open":2.2,"high":2.24,"low":2.18,"close":2.24,"adjclose":2.16,"volume":31900},{"date":"2025-04-25","open":2.24,"high":2.24,"low":2.22,"close":2.22,"adjclose":2.14,"volume":3700},{"date":"2025-04-28","open":2.22,"high":2.26,"low":2.22,"close":2.24,"adjclose":2.16,"volume":14000},{"date":"2025-04-29","open":2.26,"high":2.3,"low":2.24,"close":2.3,"adjclose":2.21,"volume":65300},{"date":"2025-04-30","open":2.28,"high":2.3,"low":2.28,"close":2.3,"adjclose":2.21,"volume":8400},{"date":"2025-05-02","open":2.24,"high":2.3,"low":2.24,"close":2.3,"adjclose":2.21,"volume":2100},{"date":"2025-05-06","open":2.28,"high":2.28,"low":2.22,"close":2.28,"adjclose":2.2,"volume":51700},{"date":"2025-05-07","open":2.28,"high":2.3,"low":2.24,"close":2.28,"adjclose":2.2,"volume":10300},{"date":"2025-05-08","open":2.3,"high":2.3,"low":2.28,"close":2.3,"adjclose":2.21,"volume":6300},{"date":"2025-05-09","open":2.32,"high":2.32,"low":2.24,"close":2.32,"adjclose":2.23,"volume":5800},{"date":"2025-05-13","open":2.32,"high":2.32,"low":2.3,"close":2.32,"adjclose":2.23,"volume":13200},{"date":"2025-05-14","open":2.3,"high":2.32,"low":2.3,"close":2.32,"adjclose":2.23,"volume":22300},{"date":"2025-05-15","open":2.24,"high":2.34,"low":2.2,"close":2.34,"adjclose":2.25,"volume":49400},{"date":"2025-05-16","open":2.32,"high":2.32,"low":2.28,"close":2.32,"adjclose":2.23,"volume":5100},{"date":"2025-05-19","open":2.28,"high":2.28,"low":2.22,"close":2.24,"adjclose":2.16,"volume":25900},{"date":"2025-05-20","open":2.24,"high":2.24,"low":2.1,"close":2.16,"adjclose":2.08,"volume":22300},{"date":"2025-05-21","open":2.12,"high":2.18,"low":2.1,"close":2.18,"adjclose":2.1,"volume":53200},{"date":"2025-05-22","open":2.14,"high":2.16,"low":2.14,"close":2.14,"adjclose":2.06,"volume":7100},{"date":"2025-05-23","open":2.1,"high":2.1,"low":2.1,"close":2.1,"adjclose":2.02,"volume":8200},{"date":"2025-05-26","open":2.18,"high":2.18,"low":2.18,"close":2.18,"adjclose":2.1,"volume":100},{"date":"2025-05-27","open":2.18,"high":2.18,"low":2.18,"close":2.18,"adjclose":2.1,"volume":2800},{"date":"2025-05-28","open":2.1,"high":2.18,"low":2.1,"close":2.1,"adjclose":2.02,"volume":36400},{"date":"2025-05-29","open":2.1,"high":2.1,"low":1.96,"close":2.1,"adjclose":2.02,"volume":69800},{"date":"2025-05-30","open":2.04,"high":2.06,"low":2.02,"close":2.06,"adjclose":1.98,"volume":6400},{"date":"2025-06-04","open":2.02,"high":2.06,"low":2.02,"close":2.04,"adjclose":1.96,"volume":1400},{"date":"2025-06-05","open":2.02,"high":2.04,"low":2.02,"close":2.04,"adjclose":1.96,"volume":1400},{"date":"2025-06-06","open":2,"high":2.04,"low":2,"close":2.04,"adjclose":1.96,"volume":3200},{"date":"2025-06-09","open":2.04,"high":2.04,"low":2,"close":2,"adjclose":1.93,"volume":7400},{"date":"2025-06-10","open":2.02,"high":2.02,"low":2,"close":2.02,"adjclose":1.95,"volume":79300},{"date":"2025-06-11","open":2.02,"high":2.12,"low":2.02,"close":2.12,"adjclose":2.04,"volume":59100},{"date":"2025-06-12","open":2.06,"high":2.14,"low":2.06,"close":2.14,"adjclose":2.06,"volume":205300},{"date":"2025-06-13","open":2.14,"high":2.14,"low":2.14,"close":2.14,"adjclose":2.06,"volume":194100},{"date":"2025-06-16","open":2.14,"high":2.14,"low":2.14,"close":2.14,"adjclose":2.06,"volume":17000},{"date":"2025-06-17","open":2.16,"high":2.16,"low":2.14,"close":2.14,"adjclose":2.06,"volume":96200},{"date":"2025-06-18","open":2.14,"high":2.14,"low":2.14,"close":2.14,"adjclose":2.06,"volume":23900},{"date":"2025-06-19","open":2.14,"high":2.14,"low":2.14,"close":2.14,"adjclose":2.06,"volume":10600},{"date":"2025-06-20","open":2.08,"high":2.18,"low":2.08,"close":2.18,"adjclose":2.1,"volume":400},{"date":"2025-06-23","open":2.14,"high":2.16,"low":2.14,"close":2.16,"adjclose":2.08,"volume":96600},{"date":"2025-06-24","open":2.14,"high":2.14,"low":2.14,"close":2.14,"adjclose":2.06,"volume":400},{"date":"2025-06-25","open":2.14,"high":2.16,"low":2.14,"close":2.14,"adjclose":2.06,"volume":49600},{"date":"2025-06-26","open":2.16,"high":2.16,"low":2.14,"close":2.14,"adjclose":2.06,"volume":57600},{"date":"2025-06-27","open":2.1,"high":2.16,"low":2.06,"close":2.14,"adjclose":2.06,"volume":1400},{"date":"2025-06-30","open":2.14,"high":2.16,"low":2.14,"close":2.16,"adjclose":2.08,"volume":88100},{"date":"2025-07-01","open":2.14,"high":2.14,"low":2.14,"close":2.14,"adjclose":2.06,"volume":6200},{"date":"2025-07-02","open":2.14,"high":2.14,"low":2.14,"close":2.14,"adjclose":2.06,"volume":3900},{"date":"2025-07-03","open":2.16,"high":2.2,"low":2.16,"close":2.2,"adjclose":2.12,"volume":78200},{"date":"2025-07-04","open":2.26,"high":2.26,"low":2.2,"close":2.24,"adjclose":2.16,"volume":9100},{"date":"2025-07-07","open":2.24,"high":2.24,"low":2.24,"close":2.24,"adjclose":2.16,"volume":0},{"date":"2025-07-08","open":2.34,"high":2.34,"low":2.18,"close":2.24,"adjclose":2.16,"volume":9100},{"date":"2025-07-09","open":2.24,"high":2.24,"low":2.24,"close":2.24,"adjclose":2.16,"volume":0},{"date":"2025-07-11","open":2.3,"high":2.3,"low":2.2,"close":2.26,"adjclose":2.18,"volume":8500},{"date":"2025-07-14","open":2.26,"high":2.26,"low":2.22,"close":2.24,"adjclose":2.16,"volume":5000},{"date":"2025-07-15","open":2.24,"high":2.26,"low":2.24,"close":2.26,"adjclose":2.18,"volume":27700},{"date":"2025-07-16","open":2.3,"high":2.3,"low":2.16,"close":2.2,"adjclose":2.12,"volume":37900},{"date":"2025-07-17","open":2.16,"high":2.2,"low":2.14,"close":2.2,"adjclose":2.12,"volume":1700},{"date":"2025-07-18","open":2.26,"high":2.28,"low":2.16,"close":2.22,"adjclose":2.14,"volume":52600},{"date":"2025-07-21","open":2.22,"high":2.22,"low":2.18,"close":2.2,"adjclose":2.12,"volume":59600},{"date":"2025-07-22","open":2.18,"high":2.2,"low":2.14,"close":2.18,"adjclose":2.1,"volume":55600},{"date":"2025-07-23","open":2.2,"high":2.22,"low":2.12,"close":2.18,"adjclose":2.1,"volume":60500},{"date":"2025-07-24","open":2.18,"high":2.2,"low":2.18,"close":2.2,"adjclose":2.12,"volume":10800},{"date":"2025-07-25","open":2.2,"high":2.22,"low":2.16,"close":2.22,"adjclose":2.14,"volume":16300},{"date":"2025-07-29","open":2.22,"high":2.22,"low":2.22,"close":2.22,"adjclose":2.14,"volume":27200},{"date":"2025-07-30","open":2.34,"high":2.34,"low":2.2,"close":2.2,"adjclose":2.12,"volume":72900},{"date":"2025-07-31","open":2.26,"high":2.26,"low":2.22,"close":2.26,"adjclose":2.18,"volume":900},{"date":"2025-08-01","open":2.26,"high":2.3,"low":2.24,"close":2.28,"adjclose":2.2,"volume":6000},{"date":"2025-08-04","open":2.32,"high":2.32,"low":2.3,"close":2.3,"adjclose":2.21,"volume":4700},{"date":"2025-08-05","open":2.26,"high":2.26,"low":2.12,"close":2.2,"adjclose":2.12,"volume":56000},{"date":"2025-08-06","open":2.22,"high":2.24,"low":2.14,"close":2.14,"adjclose":2.06,"volume":35300},{"date":"2025-08-07","open":2.22,"high":2.24,"low":2.14,"close":2.14,"adjclose":2.06,"volume":42700},{"date":"2025-08-08","open":2.18,"high":2.18,"low":2.08,"close":2.08,"adjclose":2,"volume":38100},{"date":"2025-08-13","open":2.08,"high":2.14,"low":2.08,"close":2.08,"adjclose":2,"volume":55300},{"date":"2025-08-14","open":2.06,"high":2.08,"low":2.04,"close":2.04,"adjclose":1.96,"volume":49400},{"date":"2025-08-15","open":2.12,"high":2.12,"low":2,"close":2,"adjclose":1.93,"volume":33500},{"date":"2025-08-18","open":2.08,"high":2.08,"low":2,"close":2,"adjclose":1.93,"volume":49500},{"date":"2025-08-19","open":2,"high":2.06,"low":2,"close":2.04,"adjclose":1.96,"volume":32700},{"date":"2025-08-20","open":2,"high":2.04,"low":2,"close":2,"adjclose":1.93,"volume":13700},{"date":"2025-08-21","open":2,"high":2.04,"low":2,"close":2.02,"adjclose":1.95,"volume":53600},{"date":"2025-08-22","open":2,"high":2.08,"low":2,"close":2.04,"adjclose":1.96,"volume":51100},{"date":"2025-08-25","open":2.08,"high":2.08,"low":2,"close":2,"adjclose":1.93,"volume":95400},{"date":"2025-08-26","open":2.06,"high":2.06,"low":2.02,"close":2.02,"adjclose":1.95,"volume":16700},{"date":"2025-08-27","open":2.06,"high":2.22,"low":2.06,"close":2.14,"adjclose":2.06,"volume":393300},{"date":"2025-08-28","open":2.16,"high":2.18,"low":2.16,"close":2.18,"adjclose":2.1,"volume":14900},{"date":"2025-08-29","open":2.14,"high":2.18,"low":2.14,"close":2.18,"adjclose":2.1,"volume":10500},{"date":"2025-09-01","open":2.14,"high":2.2,"low":2.14,"close":2.2,"adjclose":2.12,"volume":10100},{"date":"2025-09-02","open":2.2,"high":2.2,"low":2.14,"close":2.2,"adjclose":2.12,"volume":12600},{"date":"2025-09-03","open":2.22,"high":2.22,"low":2.18,"close":2.18,"adjclose":2.1,"volume":15800},{"date":"2025-09-04","open":2.2,"high":2.22,"low":2.2,"close":2.22,"adjclose":2.14,"volume":61600},{"date":"2025-09-05","open":2.22,"high":2.22,"low":2.22,"close":2.22,"adjclose":2.14,"volume":2300},{"date":"2025-09-08","open":2.22,"high":2.24,"low":2.22,"close":2.24,"adjclose":2.16,"volume":27100},{"date":"2025-09-09","open":2.24,"high":2.26,"low":2.22,"close":2.22,"adjclose":2.14,"volume":10100},{"date":"2025-09-10","open":2.26,"high":2.26,"low":2.22,"close":2.22,"adjclose":2.14,"volume":800},{"date":"2025-09-11","open":2.24,"high":2.24,"low":2.24,"close":2.24,"adjclose":2.16,"volume":600},{"date":"2025-09-12","open":2.22,"high":2.24,"low":2.16,"close":2.16,"adjclose":2.08,"volume":16800},{"date":"2025-09-15","open":2.16,"high":2.22,"low":2.14,"close":2.2,"adjclose":2.12,"volume":92500},{"date":"2025-09-16","open":2.22,"high":2.22,"low":2.18,"close":2.18,"adjclose":2.1,"volume":800},{"date":"2025-09-17","open":2.18,"high":2.2,"low":2.16,"close":2.2,"adjclose":2.12,"volume":7700},{"date":"2025-09-18","open":2.16,"high":2.2,"low":2.14,"close":2.2,"adjclose":2.12,"volume":6700},{"date":"2025-09-19","open":2.16,"high":2.2,"low":2.16,"close":2.2,"adjclose":2.12,"volume":700},{"date":"2025-09-22","open":2.16,"high":2.2,"low":2.16,"close":2.2,"adjclose":2.12,"volume":3800},{"date":"2025-09-23","open":2.16,"high":2.2,"low":2.16,"close":2.2,"adjclose":2.12,"volume":6200},{"date":"2025-09-24","open":2.18,"high":2.2,"low":2.16,"close":2.18,"adjclose":2.1,"volume":6200},{"date":"2025-09-25","open":2.2,"high":2.2,"low":2.18,"close":2.18,"adjclose":2.1,"volume":400},{"date":"2025-09-26","open":2.18,"high":2.2,"low":2.18,"close":2.18,"adjclose":2.1,"volume":66500},{"date":"2025-09-29","open":2.2,"high":2.22,"low":2.18,"close":2.18,"adjclose":2.1,"volume":1200},{"date":"2025-09-30","open":2.18,"high":2.2,"low":2.16,"close":2.2,"adjclose":2.12,"volume":19800},{"date":"2025-10-01","open":2.2,"high":2.2,"low":2.14,"close":2.2,"adjclose":2.12,"volume":2500},{"date":"2025-10-02","open":2.2,"high":2.2,"low":2.14,"close":2.14,"adjclose":2.06,"volume":6600},{"date":"2025-10-03","open":2.2,"high":2.2,"low":2.14,"close":2.14,"adjclose":2.06,"volume":43400},{"date":"2025-10-06","open":2.16,"high":2.2,"low":2.14,"close":2.2,"adjclose":2.12,"volume":46800},{"date":"2025-10-07","open":2.2,"high":2.2,"low":2.2,"close":2.2,"adjclose":2.12,"volume":0},{"date":"2025-10-08","open":2.2,"high":2.2,"low":2.2,"close":2.2,"adjclose":2.12,"volume":0},{"date":"2025-10-09","open":2.14,"high":2.2,"low":2.14,"close":2.2,"adjclose":2.12,"volume":600},{"date":"2025-10-10","open":2.18,"high":2.2,"low":2.16,"close":2.2,"adjclose":2.12,"volume":70200},{"date":"2025-10-14","open":2.2,"high":2.2,"low":2.14,"close":2.16,"adjclose":2.08,"volume":4100},{"date":"2025-10-15","open":2.16,"high":2.2,"low":2.16,"close":2.2,"adjclose":2.12,"volume":9900},{"date":"2025-10-16","open":2.2,"high":2.2,"low":2.18,"close":2.2,"adjclose":2.12,"volume":17100},{"date":"2025-10-17","open":2.14,"high":2.2,"low":2.14,"close":2.14,"adjclose":2.06,"volume":1200},{"date":"2025-10-20","open":2.16,"high":2.18,"low":2.14,"close":2.18,"adjclose":2.1,"volume":4700},{"date":"2025-10-21","open":2.2,"high":2.2,"low":2.14,"close":2.16,"adjclose":2.08,"volume":2300},{"date":"2025-10-22","open":2.14,"high":2.18,"low":2.14,"close":2.18,"adjclose":2.1,"volume":374900},{"date":"2025-10-24","open":2.16,"high":2.16,"low":2.14,"close":2.16,"adjclose":2.08,"volume":131700},{"date":"2025-10-27","open":2.18,"high":2.18,"low":2.18,"close":2.18,"adjclose":2.1,"volume":300},{"date":"2025-10-28","open":2.14,"high":2.18,"low":2.14,"close":2.18,"adjclose":2.1,"volume":38200},{"date":"2025-10-29","open":2.18,"high":2.18,"low":2.18,"close":2.18,"adjclose":2.1,"volume":0},{"date":"2025-10-30","open":2.16,"high":2.16,"low":2.14,"close":2.14,"adjclose":2.06,"volume":38300},{"date":"2025-10-31","open":2.18,"high":2.18,"low":2.14,"close":2.16,"adjclose":2.08,"volume":8300},{"date":"2025-11-03","open":2.14,"high":2.16,"low":2.14,"close":2.14,"adjclose":2.06,"volume":84700},{"date":"2025-11-04","open":2.14,"high":2.14,"low":2.14,"close":2.14,"adjclose":2.06,"volume":54800},{"date":"2025-11-05","open":2.16,"high":2.16,"low":2.16,"close":2.16,"adjclose":2.08,"volume":20000},{"date":"2025-11-06","open":2.18,"high":2.18,"low":2.18,"close":2.18,"adjclose":2.1,"volume":35000},{"date":"2025-11-07","open":2.18,"high":2.18,"low":2.14,"close":2.16,"adjclose":2.08,"volume":500},{"date":"2025-11-10","open":2.16,"high":2.16,"low":2.1,"close":2.1,"adjclose":2.02,"volume":5300},{"date":"2025-11-11","open":2.12,"high":2.14,"low":2.06,"close":2.14,"adjclose":2.06,"volume":1100},{"date":"2025-11-12","open":2.14,"high":2.14,"low":2.12,"close":2.12,"adjclose":2.04,"volume":120400},{"date":"2025-11-13","open":2.12,"high":2.12,"low":2.12,"close":2.12,"adjclose":2.04,"volume":400},{"date":"2025-11-14","open":2.1,"high":2.1,"low":2.06,"close":2.06,"adjclose":1.98,"volume":3700},{"date":"2025-11-17","open":2.04,"high":2.08,"low":2,"close":2.08,"adjclose":2,"volume":14800},{"date":"2025-11-18","open":2.04,"high":2.04,"low":2.02,"close":2.02,"adjclose":1.95,"volume":1800},{"date":"2025-11-19","open":2.02,"high":2.02,"low":2.02,"close":2.02,"adjclose":1.95,"volume":1200},{"date":"2025-11-20","open":2.08,"high":2.08,"low":2.08,"close":2.08,"adjclose":2,"volume":2000},{"date":"2025-11-21","open":2.08,"high":2.08,"low":2,"close":2.08,"adjclose":2,"volume":900},{"date":"2025-11-24","open":2,"high":2.06,"low":2,"close":2.06,"adjclose":1.98,"volume":4100},{"date":"2025-11-25","open":2.08,"high":2.08,"low":2,"close":2,"adjclose":1.93,"volume":6400},{"date":"2025-11-26","open":2.08,"high":2.08,"low":2.08,"close":2.08,"adjclose":2,"volume":100},{"date":"2025-11-27","open":2.08,"high":2.08,"low":2.08,"close":2.08,"adjclose":2,"volume":0},{"date":"2025-11-28","open":2.08,"high":2.08,"low":2.08,"close":2.08,"adjclose":2,"volume":0},{"date":"2025-12-01","open":1.94,"high":1.95,"low":1.94,"close":1.95,"adjclose":1.88,"volume":2300},{"date":"2025-12-02","open":1.99,"high":2,"low":1.99,"close":1.99,"adjclose":1.92,"volume":1800},{"date":"2025-12-03","open":2,"high":2,"low":2,"close":2,"adjclose":1.93,"volume":700},{"date":"2025-12-04","open":1.95,"high":1.95,"low":1.95,"close":1.95,"adjclose":1.88,"volume":22600},{"date":"2025-12-08","open":1.95,"high":1.95,"low":1.95,"close":1.95,"adjclose":1.88,"volume":3200},{"date":"2025-12-09","open":1.94,"high":1.94,"low":1.91,"close":1.91,"adjclose":1.84,"volume":2000},{"date":"2025-12-11","open":1.91,"high":1.94,"low":1.91,"close":1.94,"adjclose":1.87,"volume":2600},{"date":"2025-12-12","open":1.96,"high":1.98,"low":1.92,"close":1.92,"adjclose":1.85,"volume":20500},{"date":"2025-12-15","open":1.98,"high":1.98,"low":1.98,"close":1.98,"adjclose":1.91,"volume":2700},{"date":"2025-12-16","open":1.98,"high":1.98,"low":1.98,"close":1.98,"adjclose":1.91,"volume":500},{"date":"2025-12-17","open":1.96,"high":1.98,"low":1.96,"close":1.96,"adjclose":1.89,"volume":5800},{"date":"2025-12-18","open":1.96,"high":1.96,"low":1.96,"close":1.96,"adjclose":1.89,"volume":200},{"date":"2025-12-19","open":1.96,"high":1.96,"low":1.96,"close":1.96,"adjclose":1.89,"volume":300},{"date":"2025-12-22","open":2,"high":2,"low":2,"close":2,"adjclose":1.93,"volume":400},{"date":"2025-12-23","open":1.98,"high":1.98,"low":1.98,"close":1.98,"adjclose":1.91,"volume":100},{"date":"2025-12-24","open":1.99,"high":1.99,"low":1.91,"close":1.92,"adjclose":1.85,"volume":25400},{"date":"2025-12-25","open":1.98,"high":1.99,"low":1.98,"close":1.98,"adjclose":1.91,"volume":2100},{"date":"2025-12-26","open":1.99,"high":1.99,"low":1.92,"close":1.98,"adjclose":1.91,"volume":16800},{"date":"2025-12-29","open":1.92,"high":1.99,"low":1.91,"close":1.94,"adjclose":1.87,"volume":89600},{"date":"2025-12-30","open":1.91,"high":2,"low":1.91,"close":1.99,"adjclose":1.92,"volume":62500},{"date":"2026-01-05","open":1.98,"high":1.98,"low":1.91,"close":1.98,"adjclose":1.91,"volume":1200},{"date":"2026-01-06","open":1.98,"high":2,"low":1.98,"close":2,"adjclose":1.93,"volume":4100},{"date":"2026-01-07","open":2,"high":2,"low":1.93,"close":1.93,"adjclose":1.86,"volume":900},{"date":"2026-01-08","open":1.93,"high":1.95,"low":1.93,"close":1.95,"adjclose":1.88,"volume":51000},{"date":"2026-01-09","open":1.97,"high":2,"low":1.97,"close":2,"adjclose":1.93,"volume":200},{"date":"2026-01-12","open":1.99,"high":2,"low":1.93,"close":1.99,"adjclose":1.92,"volume":4700},{"date":"2026-01-13","open":1.94,"high":1.98,"low":1.93,"close":1.93,"adjclose":1.86,"volume":10200},{"date":"2026-01-14","open":1.97,"high":1.98,"low":1.97,"close":1.98,"adjclose":1.91,"volume":4300},{"date":"2026-01-15","open":1.99,"high":2,"low":1.92,"close":1.92,"adjclose":1.85,"volume":10000},{"date":"2026-01-16","open":1.99,"high":1.99,"low":1.99,"close":1.99,"adjclose":1.92,"volume":500},{"date":"2026-01-19","open":1.99,"high":1.99,"low":1.98,"close":1.98,"adjclose":1.91,"volume":800},{"date":"2026-01-20","open":1.98,"high":1.98,"low":1.98,"close":1.98,"adjclose":1.91,"volume":100},{"date":"2026-01-21","open":1.95,"high":2.02,"low":1.95,"close":1.97,"adjclose":1.9,"volume":54200},{"date":"2026-01-22","open":1.99,"high":2,"low":1.99,"close":2,"adjclose":1.93,"volume":23800},{"date":"2026-01-23","open":1.99,"high":2,"low":1.99,"close":2,"adjclose":1.93,"volume":300},{"date":"2026-01-26","open":2,"high":2.02,"low":2,"close":2.02,"adjclose":1.95,"volume":40200},{"date":"2026-01-27","open":2.12,"high":2.12,"low":2.08,"close":2.08,"adjclose":2,"volume":22200},{"date":"2026-01-28","open":2.1,"high":2.12,"low":2.1,"close":2.12,"adjclose":2.04,"volume":3200},{"date":"2026-01-29","open":2.1,"high":2.12,"low":2.08,"close":2.08,"adjclose":2,"volume":10000},{"date":"2026-01-30","open":2.1,"high":2.12,"low":2.08,"close":2.08,"adjclose":2,"volume":2200},{"date":"2026-02-02","open":2.08,"high":2.1,"low":2.08,"close":2.08,"adjclose":2,"volume":49600},{"date":"2026-02-03","open":2.1,"high":2.1,"low":2.1,"close":2.1,"adjclose":2.02,"volume":100},{"date":"2026-02-04","open":2.08,"high":2.08,"low":2.06,"close":2.06,"adjclose":1.98,"volume":200},{"date":"2026-02-05","open":2.02,"high":2.06,"low":2.02,"close":2.06,"adjclose":1.98,"volume":300},{"date":"2026-02-06","open":2.06,"high":2.1,"low":2,"close":2,"adjclose":1.93,"volume":13300},{"date":"2026-02-09","open":2.04,"high":2.1,"low":1.96,"close":2.08,"adjclose":2,"volume":14200},{"date":"2026-02-10","open":2,"high":2.04,"low":1.99,"close":2.04,"adjclose":1.96,"volume":7600},{"date":"2026-02-11","open":2.04,"high":2.1,"low":2.04,"close":2.08,"adjclose":2,"volume":600},{"date":"2026-02-12","open":2.02,"high":2.06,"low":2,"close":2.06,"adjclose":1.98,"volume":11300},{"date":"2026-02-13","open":2.06,"high":2.08,"low":2.04,"close":2.06,"adjclose":1.98,"volume":23900},{"date":"2026-02-16","open":2.08,"high":2.08,"low":2.06,"close":2.06,"adjclose":1.98,"volume":13900},{"date":"2026-02-17","open":2.02,"high":2.08,"low":2.02,"close":2.08,"adjclose":2,"volume":18600},{"date":"2026-02-18","open":2.08,"high":2.1,"low":2.08,"close":2.1,"adjclose":2.02,"volume":6100},{"date":"2026-02-19","open":2.1,"high":2.1,"low":2.08,"close":2.08,"adjclose":2,"volume":2100},{"date":"2026-02-20","open":2.08,"high":2.12,"low":2.08,"close":2.1,"adjclose":2.02,"volume":13500},{"date":"2026-02-23","open":2.12,"high":2.12,"low":2.12,"close":2.12,"adjclose":2.04,"volume":100},{"date":"2026-02-24","open":2.1,"high":2.12,"low":2.1,"close":2.12,"adjclose":2.04,"volume":1100},{"date":"2026-02-25","open":2.12,"high":2.12,"low":2.08,"close":2.1,"adjclose":2.02,"volume":13800},{"date":"2026-02-26","open":2.12,"high":2.12,"low":2.1,"close":2.1,"adjclose":2.02,"volume":600},{"date":"2026-02-27","open":2.12,"high":2.12,"low":2.06,"close":2.12,"adjclose":2.04,"volume":11100},{"date":"2026-03-02","open":2.04,"high":2.14,"low":2.04,"close":2.14,"adjclose":2.06,"volume":38100},{"date":"2026-03-04","open":2.06,"high":2.1,"low":2,"close":2.1,"adjclose":2.02,"volume":51800},{"date":"2026-03-05","open":2.08,"high":2.08,"low":2.08,"close":2.08,"adjclose":2,"volume":100},{"date":"2026-03-06","open":2.02,"high":2.06,"low":2.02,"close":2.06,"adjclose":1.98,"volume":17600},{"date":"2026-03-09","open":2.06,"high":2.06,"low":1.99,"close":2.02,"adjclose":1.95,"volume":54500},{"date":"2026-03-10","open":2.04,"high":2.06,"low":2,"close":2.04,"adjclose":1.96,"volume":29400},{"date":"2026-03-11","open":2.02,"high":2.1,"low":2.02,"close":2.1,"adjclose":2.02,"volume":20800},{"date":"2026-03-12","open":2.04,"high":2.08,"low":2.04,"close":2.08,"adjclose":2,"volume":23300},{"date":"2026-03-13","open":2.08,"high":2.1,"low":2.08,"close":2.1,"adjclose":2.02,"volume":600},{"date":"2026-03-16","open":2.02,"high":2.08,"low":2,"close":2.08,"adjclose":2,"volume":16900},{"date":"2026-03-17","open":2.1,"high":2.1,"low":2.08,"close":2.1,"adjclose":2.02,"volume":14200},{"date":"2026-03-18","open":2.1,"high":2.16,"low":2.1,"close":2.16,"adjclose":2.08,"volume":33400},{"date":"2026-03-19","open":2.04,"high":2.12,"low":2.02,"close":2.12,"adjclose":2.12,"volume":27600},{"date":"2026-03-20","open":2.1,"high":2.1,"low":2.08,"close":2.1,"adjclose":2.1,"volume":35600},{"date":"2026-03-23","open":2.1,"high":2.1,"low":2.1,"close":2.1,"adjclose":2.1,"volume":57000},{"date":"2026-03-24","open":2.1,"high":2.12,"low":2.1,"close":2.12,"adjclose":2.12,"volume":9500},{"date":"2026-03-25","open":2.12,"high":2.16,"low":2.12,"close":2.14,"adjclose":2.14,"volume":122100},{"date":"2026-03-26","open":2.18,"high":2.26,"low":2.18,"close":2.22,"adjclose":2.22,"volume":40100},{"date":"2026-03-27","open":2.2,"high":2.32,"low":2.2,"close":2.32,"adjclose":2.32,"volume":79000},{"date":"2026-03-30","open":2.34,"high":2.58,"low":2.32,"close":2.46,"adjclose":2.46,"volume":238900},{"date":"2026-03-31","open":2.56,"high":2.56,"low":2.46,"close":2.5,"adjclose":2.5,"volume":229400},{"date":"2026-04-01","open":2.54,"high":2.54,"low":2.46,"close":2.54,"adjclose":2.54,"volume":5900},{"date":"2026-04-02","open":2.46,"high":2.54,"low":2.42,"close":2.54,"adjclose":2.54,"volume":10800},{"date":"2026-04-03","open":2.52,"high":2.52,"low":2.4,"close":2.44,"adjclose":2.44,"volume":27900},{"date":"2026-04-07","open":2.5,"high":2.5,"low":2.4,"close":2.42,"adjclose":2.42,"volume":28600},{"date":"2026-04-08","open":2.4,"high":2.44,"low":2.4,"close":2.4,"adjclose":2.4,"volume":11900},{"date":"2026-04-09","open":2.4,"high":2.4,"low":2.38,"close":2.38,"adjclose":2.38,"volume":33000},{"date":"2026-04-10","open":2.42,"high":2.42,"low":2.34,"close":2.4,"adjclose":2.4,"volume":7700},{"date":"2026-04-16","open":2.38,"high":2.42,"low":2.38,"close":2.42,"adjclose":2.42,"volume":3300},{"date":"2026-04-17","open":2.38,"high":2.42,"low":2.38,"close":2.42,"adjclose":2.42,"volume":300},{"date":"2026-04-20","open":2.4,"high":2.4,"low":2.34,"close":2.4,"adjclose":2.4,"volume":1000},{"date":"2026-04-21","open":2.34,"high":2.42,"low":2.32,"close":2.42,"adjclose":2.42,"volume":5800},{"date":"2026-04-22","open":2.34,"high":2.34,"low":2.3,"close":2.34,"adjclose":2.34,"volume":15300},{"date":"2026-04-23","open":2.34,"high":2.34,"low":2.34,"close":2.34,"adjclose":2.34,"volume":0},{"date":"2026-04-24","open":2.34,"high":2.34,"low":2.34,"close":2.34,"adjclose":2.34,"volume":0},{"date":"2026-04-27","open":2.3,"high":2.3,"low":2.3,"close":2.3,"adjclose":2.3,"volume":2000},{"date":"2026-04-28","open":2.34,"high":2.34,"low":2.3,"close":2.3,"adjclose":2.3,"volume":3000},{"date":"2026-04-29","open":2.3,"high":2.34,"low":2.3,"close":2.34,"adjclose":2.34,"volume":9400},{"date":"2026-04-30","open":2.34,"high":2.38,"low":2.34,"close":2.38,"adjclose":2.38,"volume":11000},{"date":"2026-05-01","open":2.38,"high":2.38,"low":2.38,"close":2.38,"adjclose":2.38,"volume":0},{"date":"2026-05-04","open":2.38,"high":2.38,"low":2.38,"close":2.38,"adjclose":2.38,"volume":0},{"date":"2026-05-05","open":2.38,"high":2.38,"low":2.38,"close":2.38,"adjclose":2.38,"volume":0},{"date":"2026-05-06","open":2.3,"high":2.36,"low":2.3,"close":2.36,"adjclose":2.36,"volume":4600},{"date":"2026-05-07","open":2.38,"high":2.5,"low":2.38,"close":2.46,"adjclose":2.46,"volume":59500},{"date":"2026-05-08","open":2.44,"high":2.62,"low":2.44,"close":2.62,"adjclose":2.62,"volume":70400},{"date":"2026-05-11","open":2.56,"high":2.56,"low":2.46,"close":2.54,"adjclose":2.54,"volume":14500},{"date":"2026-05-12","open":2.5,"high":2.58,"low":2.42,"close":2.5,"adjclose":2.5,"volume":15600},{"date":"2026-05-13","open":2.44,"high":2.5,"low":2.44,"close":2.5,"adjclose":2.5,"volume":500},{"date":"2026-05-14","open":2.5,"high":2.5,"low":2.46,"close":2.46,"adjclose":2.46,"volume":17200},{"date":"2026-05-15","open":2.42,"high":2.42,"low":2.34,"close":2.34,"adjclose":2.34,"volume":84700},{"date":"2026-05-18","open":2.34,"high":2.34,"low":2.3,"close":2.32,"adjclose":2.32,"volume":50400},{"date":"2026-05-19","open":2.3,"high":2.3,"low":2.28,"close":2.28,"adjclose":2.28,"volume":3200},{"date":"2026-05-20","open":2.26,"high":2.3,"low":2.26,"close":2.3,"adjclose":2.3,"volume":1700},{"date":"2026-05-21","open":2.3,"high":2.3,"low":2.3,"close":2.3,"adjclose":2.3,"volume":0},{"date":"2026-05-22","open":2.28,"high":2.28,"low":2.26,"close":2.28,"adjclose":2.28,"volume":7000},{"date":"2026-05-25","open":2.28,"high":2.28,"low":2.24,"close":2.26,"adjclose":2.26,"volume":6200},{"date":"2026-05-26","open":2.26,"high":2.28,"low":2.26,"close":2.28,"adjclose":2.28,"volume":13800},{"date":"2026-05-27","open":2.28,"high":2.28,"low":2.26,"close":2.26,"adjclose":2.26,"volume":8100},{"date":"2026-05-28","open":2.26,"high":2.26,"low":2.22,"close":2.22,"adjclose":2.22,"volume":35900},{"date":"2026-05-29","open":2.24,"high":2.24,"low":2.22,"close":2.24,"adjclose":2.24,"volume":3500},{"date":"2026-06-01","open":2.24,"high":2.24,"low":2.24,"close":2.24,"adjclose":2.24,"volume":0},{"date":"2026-06-02","open":2.22,"high":2.22,"low":2.2,"close":2.2,"adjclose":2.2,"volume":16000},{"date":"2026-06-03","open":2.2,"high":2.2,"low":2.2,"close":2.2,"adjclose":2.2,"volume":0},{"date":"2026-06-04","open":2.2,"high":2.2,"low":2.16,"close":2.16,"adjclose":2.16,"volume":28000},{"date":"2026-06-05","open":2.16,"high":2.18,"low":2.12,"close":2.12,"adjclose":2.12,"volume":62700},{"date":"2026-06-08","open":2.16,"high":2.16,"low":2.16,"close":2.16,"adjclose":2.16,"volume":300},{"date":"2026-06-09","open":2.14,"high":2.16,"low":2.14,"close":2.16,"adjclose":2.16,"volume":10600},{"date":"2026-06-10","open":2.16,"high":2.2,"low":2.16,"close":2.2,"adjclose":2.2,"volume":17700},{"date":"2026-06-11","open":2.16,"high":2.18,"low":2.16,"close":2.18,"adjclose":2.18,"volume":1200},{"date":"2026-06-12","open":2.16,"high":2.2,"low":2.16,"close":2.2,"adjclose":2.2,"volume":1100},{"date":"2026-06-15","open":2.16,"high":2.16,"low":2.1,"close":2.12,"adjclose":2.12,"volume":28800},{"date":"2026-06-16","open":2.14,"high":2.14,"low":2.14,"close":2.14,"adjclose":2.14,"volume":200},{"date":"2026-06-17","open":2.14,"high":2.14,"low":2.12,"close":2.14,"adjclose":2.14,"volume":10200},{"date":"2026-06-18","open":2.14,"high":2.16,"low":2.12,"close":2.14,"adjclose":2.14,"volume":21100},{"date":"2026-06-19","open":2.14,"high":2.14,"low":2.12,"close":2.12,"adjclose":2.12,"volume":22000},{"date":"2026-06-22","open":2.12,"high":2.12,"low":2.12,"close":2.12,"adjclose":2.12,"volume":800},{"date":"2026-06-23","open":2.1,"high":2.1,"low":2.08,"close":2.08,"adjclose":2.08,"volume":14900},{"date":"2026-06-24","open":2.06,"high":2.08,"low":2.06,"close":2.06,"adjclose":2.06,"volume":21200},{"date":"2026-06-25","open":2.04,"high":2.08,"low":2.04,"close":2.08,"adjclose":2.08,"volume":1600},{"date":"2026-06-26","open":2.08,"high":2.1,"low":2.08,"close":2.1,"adjclose":2.1,"volume":10019800},{"date":"2026-06-29","open":2.1,"high":2.12,"low":2.06,"close":2.12,"adjclose":2.12,"volume":33700},{"date":"2026-06-30","open":2.1,"high":2.1,"low":2.06,"close":2.1,"adjclose":2.1,"volume":53600},{"date":"2026-07-01","open":2.1,"high":2.1,"low":2.08,"close":2.1,"adjclose":2.1,"volume":14400},{"date":"2026-07-02","open":2.1,"high":2.1,"low":2.08,"close":2.1,"adjclose":2.1,"volume":21300},{"date":"2026-07-03","open":2.1,"high":2.1,"low":2.1,"close":2.1,"adjclose":2.1,"volume":1000},{"date":"2026-07-06","open":2.1,"high":2.1,"low":2.08,"close":2.1,"adjclose":2.1,"volume":36700}]}