{"generated_at":"2026-07-15T16:15:27.263Z","note":"วัดเฉพาะสัญญาณเทคนิค (Phase 1) บน close price — ไม่รวมค่าคอม/ปันผล/สลิปเพจ","universe":795,"horizons":[5,10,20],"baseline":{"samples":322473,"h5":{"n":322473,"avgRetPct":-0.237,"winRatePct":36.9},"h10":{"n":322473,"avgRetPct":-0.502,"winRatePct":37.1},"h20":{"n":322473,"avgRetPct":-0.969,"winRatePct":37.1}},"bySignal":{"BUY":{"samples":27591,"h5":{"n":27591,"avgRetPct":-0.153,"winRatePct":41},"h10":{"n":27591,"avgRetPct":-0.197,"winRatePct":41.9},"h20":{"n":27591,"avgRetPct":-0.008,"winRatePct":43.8}},"ACCUMULATE":{"samples":48492,"h5":{"n":48492,"avgRetPct":-0.577,"winRatePct":36.8},"h10":{"n":48492,"avgRetPct":-0.921,"winRatePct":36.7},"h20":{"n":48492,"avgRetPct":-1.322,"winRatePct":36}},"HOLD":{"samples":64214,"h5":{"n":64214,"avgRetPct":-0.697,"winRatePct":34},"h10":{"n":64214,"avgRetPct":-1.175,"winRatePct":34},"h20":{"n":64214,"avgRetPct":-1.868,"winRatePct":34.1}},"REDUCE":{"samples":67908,"h5":{"n":67908,"avgRetPct":-0.46,"winRatePct":35},"h10":{"n":67908,"avgRetPct":-0.807,"winRatePct":35.2},"h20":{"n":67908,"avgRetPct":-1.643,"winRatePct":34.3}},"SELL":{"samples":42611,"h5":{"n":42611,"avgRetPct":-0.022,"winRatePct":37.1},"h10":{"n":42611,"avgRetPct":-0.333,"winRatePct":36.9},"h20":{"n":42611,"avgRetPct":-0.969,"winRatePct":36.3}},"AVOID":{"samples":71657,"h5":{"n":71657,"avgRetPct":0.455,"winRatePct":39.9},"h10":{"n":71657,"avgRetPct":0.455,"winRatePct":40.2},"h20":{"n":71657,"avgRetPct":0.343,"winRatePct":41.3}}}}